workflows/__init__.py
workflows/core.py
workflows/standard.py
workflows/connectors/__init__.py
workflows/connectors/bigquery.py
workflows/connectors/firestore.py
workflows/connectors/pubsub.py
workflows/connectors/secretmanager.py
workflows/connectors/sql.py
workflows/connectors/storage.py
workflows/connectors/translate.py
workflows/connectors/vision.py
cloud_workflows-0.0.1.dist-info/LICENCE.txt
cloud_workflows-0.0.1.dist-info/METADATA
cloud_workflows-0.0.1.dist-info/WHEEL
cloud_workflows-0.0.1.dist-info/top_level.txt
cloud_workflows-0.0.1.dist-info/RECORD
