Metadata-Version: 2.1
Name: cloud-workflows
Version: 0.0.1
Summary: Unoffical SDK for Cloud Workflows
Home-page: https://github.com/zdenulo/cloud-workflows
Author: Zdenko Hrček
Author-email: zdenulo@gmail.com
License: MIT
Platform: UNKNOWN
Classifier: Development Status :: 3 - Alpha
Classifier: Intended Audience :: Developers
Classifier: License :: OSI Approved :: MIT License
Classifier: Programming Language :: Python :: 3
Classifier: Programming Language :: Python :: 3.9
License-File: LICENCE.txt
Requires-Dist: pyyaml
Requires-Dist: yamlable
